{
  "terraform": [
    {
      "required_providers": [
        {
          "aws": {
            "source": "hashicorp/aws",
            "version": ">= 2.7.0"
          }
        }
      ]
    }
  ],
  "provider": [
    {
      "aws": [
        {
          "region": "us-west-2"
        }
      ]
    }
  ],
  "resource": [
    {
      "aws_s3_bucket": [
        {
          "terraform_backend_bucket": [
            {
              "bucket": "terraform-state-ja4l20gt2vhjqlslr99azkjpmk7verni93e0fewukdkh5"
            }
          ]
        }
      ]
    },
    {
      "aws_instance": [
        {
          "test-derek": [
            {
              "ami": "${data.aws_ami.amazon_latest.id}",
              "instance_type": "t2.small",
              "lifecycle": [
                {
                  "ignore_changes": [
                    "ami"
                  ]
                }
              ]
            }
          ]
        }
      ]
    }
  ],
  "data": [
    {
      "aws_ami": [
        {
          "amazon_latest": [
            {
              "most_recent": true,
              "owners": [
                "585441382316"
              ],
              "filter": [
                {
                  "name": "name",
                  "values": [
                    "*AmazonLinux*"
                  ]
                },
                {
                  "name": "virtualization-type",
                  "values": [
                    "hvm"
                  ]
                }
              ]
            }
          ]
        }
      ]
    }
  ]
}
